nibcq/__init__.py
nibcq/_acir.py
nibcq/_calibrator.py
nibcq/_dcir.py
nibcq/_device.py
nibcq/_eis.py
nibcq/_ocv.py
nibcq/_self_cal_logic/__init__.py
nibcq/_self_cal_logic/_dmm_logic.py
nibcq/_self_cal_logic/_self_cal_factory.py
nibcq/_self_cal_logic/_smu_logic.py
nibcq/_self_cal_logic/base.py
nibcq/calibration.py
nibcq/compensation.py
nibcq/constants.py
nibcq/enums.py
nibcq/errors.py
nibcq/measurement.py
nibcq/switch.py
nibcq/temperature.py
nibcq-1.3.0.dist-info/LICENSE
nibcq-1.3.0.dist-info/METADATA
nibcq-1.3.0.dist-info/NOTICE
nibcq-1.3.0.dist-info/WHEEL
nibcq-1.3.0.dist-info/RECORD
