Metadata-Version: 2.3
Name: nibcq
Version: 1.3.0
Summary: NI Battery Cell Quality library
License: MIT
Author: Mate Vagner
Author-email: mate.vagner@emerson.com
Requires-Python: <4.0,>=3.12
Classifier: License :: OSI Approved :: MIT License
Classifier: Programming Language :: Python :: 3
Classifier: Programming Language :: Python :: 3.12
Classifier: Programming Language :: Python :: 3.13
Requires-Dist: nidaqmx (>=1.2.0,<2.0.0)
Requires-Dist: nidcpower (>=1.5.0,<2.0.0)
Requires-Dist: nidmm (>=1.4.9,<2.0.0)
Requires-Dist: niswitch (>=1.4.9,<2.0.0)
Project-URL: Documentation, https://ni.github.io/nibcq-python
Project-URL: Repository, https://github.com/ni/nibcq-python
Project-URL: Toolkit Overview, https://www.ni.com/docs/en-US/bundle/battery-cell-quality-toolkit/page/overview.html
Project-URL: Toolkit Download, https://www.ni.com/en/support/downloads/software-products/download.battery-cell-quality-toolkit.html
